[
  {
    "name": "Luinary Gallery",
    "origin": "Manila, Philippines",
    "style": "Various",
    "email": "contact@gallery.com",
    "bio": "Spiritual and metaphysical digital art printed on metal sheets.",
    "profile_image": null
  },
  {
    "name": "Woodlands",
    "origin": "Portland, USA",
    "style": "Woodwork",
    "email": "woodlands@example.com",
    "bio": "Specializing in handcrafted wooden decor and sculptures inspired by nature.",
    "profile_image": null
  },
  {
    "name": "Ceramic Sit",
    "origin": "Berlin, Germany",
    "style": "Ceramics",
    "email": "ceramicsit@example.com",
    "bio": "Modern ceramic art pieces designed for contemporary home decoration.",
    "profile_image": null
  },
  {
    "name": "Sartigas",
    "origin": "Barcelona, Spain",
    "style": "Digital & Paper",
    "email": "sartigas@example.com",
    "bio": "Contemporary digital art focused on geometric patterns and vibrant tones.",
    "profile_image": null
  },
  {
    "name": "Sardigas",
    "origin": "Madrid, Spain",
    "style": "Natural Installations",
    "email": "sardigas@example.com",
    "bio": "Focusing on natural stem, floral arrangements, and dried botanical art.",
    "profile_image": null
  },
  {
    "name": "Paganini Arts",
    "origin": "Florence, Italy",
    "style": "Pottery",
    "email": "paganini@example.com",
    "bio": "Classic Italian pottery designs mixing tradition with modern utility.",
    "profile_image": null
  },
  {
    "name": "Hansana",
    "origin": "Kyoto, Japan",
    "style": "Charcoal Sketch",
    "email": "hansana@example.com",
    "bio": "Detailed charcoal portraits capturing the soul of pets and animals.",
    "profile_image": null
  },
  {
    "name": "AStDaya",
    "origin": "Jakarta, Indonesia",
    "style": "Graphite",
    "email": "astdaya@example.com",
    "bio": "Hyper-realistic graphite pencil portraits known for incredible detail.",
    "profile_image": null
  },
  {
    "name": "ART2YOUcreation",
    "origin": "Paris, France",
    "style": "Pencil Sketch",
    "email": "art2you@example.com",
    "bio": "Custom hand-drawn portraits delivered directly to art lovers.",
    "profile_image": null
  },
  {
    "name": "MichaelJArts",
    "origin": "Toronto, Canada",
    "style": "Emotive Sketch",
    "email": "michaelj@example.com",
    "bio": "Emotive sketches capturing intimate family moments and expressions.",
    "profile_image": null
  },
  {
    "name": "yourstruly",
    "origin": "London, UK",
    "style": "Whimsical",
    "email": "yours@example.com",
    "bio": "Fun and quirky portraits of pets dressed in formal suits.",
    "profile_image": null
  },
  {
    "name": "Luinette Belen",
    "origin": "Manila, Philippines",
    "style": "Abstract",
    "email": "luinette@example.com",
    "bio": "Vibrant abstract paintings showcasing expressive strokes and local colors.",
    "profile_image": null
  },
  {
    "name": "denCepada",
    "origin": "Sao Paulo, Brazil",
    "style": "Oil Painting",
    "email": "den@example.com",
    "bio": "Oil on canvas featuring serene tones and calming landscapes.",
    "profile_image": null
  },
  {
    "name": "Shan Arts",
    "origin": "Beijing, China",
    "style": "Oil Painting",
    "email": "shan@example.com",
    "bio": "Richly detailed oil paintings with expressive, traditional brushwork.",
    "profile_image": null
  },
  {
    "name": "Leti Watersong",
    "origin": "Sydney, Australia",
    "style": "Acrylic",
    "email": "leti@example.com",
    "bio": "Part of the renowned Pag Akbay series, exploring connection through acrylics.",
    "profile_image": null
  },
  {
    "name": "Wouter van der Vlugt",
    "origin": "Amsterdam, Netherlands",
    "style": "Sculpture",
    "email": "wouter@example.com",
    "bio": "Contemporary wooden sculptures focusing on form, shadow, and negative space.",
    "profile_image": null
  },
  {
    "name": "Francesca Bernardini",
    "origin": "Rome, Italy",
    "style": "Marble",
    "email": "francesca@example.com",
    "bio": "Elegant marble sculptures representing unity and fluidity.",
    "profile_image": null
  },
  {
    "name": "Eric Valat",
    "origin": "Lyon, France",
    "style": "Bronze",
    "email": "eric@example.com",
    "bio": "Finely crafted animal sculptures with a touch of surrealism.",
    "profile_image": null
  },
  {
    "name": "Franck K",
    "origin": "Paris, France",
    "style": "Metal",
    "email": "franck@example.com",
    "bio": "Stainless steel masterpieces embodying harmony and reflection.",
    "profile_image": null
  },
  {
    "name": "Marie Louise Sorbac",
    "origin": "Brussels, Belgium",
    "style": "Marble",
    "email": "marie@example.com",
    "bio": "Graceful and fluid marble sculptures inspired by the female form.",
    "profile_image": null
  },
  {
    "name": "Mattia Bosco",
    "origin": "Milan, Italy",
    "style": "Stone",
    "email": "mattia@example.com",
    "bio": "Intricately carved sculptures emphasizing the natural texture of stone.",
    "profile_image": null
  },
  {
    "name": "Christian Løgstrup",
    "origin": "Copenhagen, Denmark",
    "style": "Digital Print",
    "email": "christian@example.com",
    "bio": "High-definition digital art prints exploring modern aesthetics.",
    "profile_image": null
  },
  {
    "name": "Fikry Botros",
    "origin": "Cairo, Egypt",
    "style": "Digital",
    "email": "fikry@example.com",
    "bio": "Digital works focusing on the dramatic interplay of light and shadow.",
    "profile_image": null
  },
  {
    "name": "Lynne Godina-orme",
    "origin": "New York, USA",
    "style": "Digital Diptych",
    "email": "lynne@example.com",
    "bio": "Vibrant diptych digital creations that tell a story across two panels.",
    "profile_image": null
  },
  {
    "name": "Michael Filonow",
    "origin": "Moscow, Russia",
    "style": "Digital Floral",
    "email": "filonow@example.com",
    "bio": "Floral majesty captured in high-resolution digital formats.",
    "profile_image": null
  },
  {
    "name": "Jason Lincoln Jeffers",
    "origin": "Sedona, USA",
    "style": "Digital on Metal",
    "email": "jason@example.com",
    "bio": "Spiritual and metaphysical digital art printed on metal sheets.",
    "profile_image": null
  },
  {
    "name": "Esteban Vera",
    "origin": "Mexico City, Mexico",
    "style": "Digital Landscape",
    "email": "esteban@example.com",
    "bio": "Searching for peace through serene digital landscapes.",
    "profile_image": null
  }
]